cobra_hdwallet/__init__.py
cobra_hdwallet-0.3.1.dist-info/LICENSE
cobra_hdwallet-0.3.1.dist-info/METADATA
cobra_hdwallet-0.3.1.dist-info/WHEEL
cobra_hdwallet-0.3.1.dist-info/top_level.txt
cobra_hdwallet-0.3.1.dist-info/RECORD
