Metadata-Version: 2.1
Name: cobra-hdwallet
Version: 0.3.1
Summary: It's HDWallet Generator for Ethereum blockchain.
Home-page: https://github.com/cobraframework/cobra-hdwallet
Author: Meheret Tesfaye
Author-email: meherett@zoho.com
License: MIT
Platform: UNKNOWN
Classifier: Development Status :: 4 - Beta
Classifier: License :: OSI Approved :: MIT License
Classifier: Programming Language :: Python :: 3.5
Classifier: Programming Language :: Python :: 3.6
Classifier: Programming Language :: Python :: 3.7
Requires-Python: >=3.6,<4
Requires-Dist: ecdsa (==0.13)
Requires-Dist: base58 (==0.2.2)
Requires-Dist: pysha3 (==1.0.2)
Requires-Dist: mnemonic (==0.13)
Requires-Dist: eth-keyfile (==0.5.1)
